mysqldave_package/.schemawiz_config2
mysqldave_package/__init__.py
mysqldave_package/excelit.py
mysqldave_package/mysqldave.py
mysqldave_package/rbc_avm_postal_code.csv
mysqldave_package/restored_sample.ddl
mysqldave_package/sample.csv
mysqldave_package/testcase1.csv
mysqldave_package/this.tsv
mysqldave_package-2.1.0.dist-info/METADATA
mysqldave_package-2.1.0.dist-info/WHEEL
mysqldave_package-2.1.0.dist-info/licenses/LICENSE
mysqldave_package-2.1.0.dist-info/RECORD
